fickle/__init__.py
fickle/exc.py
fickle/firewall.py
fickle/unpickler.py
fickle/util.py
fickle/ext/__init__.py
fickle/ext/marshmallow.py
fickle/ext/pytorch.py
fickle-0.2.2.dist-info/METADATA
fickle-0.2.2.dist-info/WHEEL
fickle-0.2.2.dist-info/top_level.txt
fickle-0.2.2.dist-info/RECORD
