Metadata-Version: 2.1
Name: fickle
Version: 0.2.2
Summary: load pickled data as safely as possible
Home-page: UNKNOWN
Author: Eduard Christian Dumitrescu
Author-email: eduard.c.dumitrescu@gmail.com
License: MIT
Platform: UNKNOWN
Classifier: Programming Language :: Python :: 3
Classifier: License :: OSI Approved :: MIT License
Classifier: Operating System :: OS Independent
Requires-Dist: attrs
